{
  "project_info": {
    "project_number": "248452815694",
    "firebase_url": "https://flutter-delivery-efa31-default-rtdb.asia-southeast1.firebasedatabase.app",
    "project_id": "flutter-delivery-efa31",
    "storage_bucket": "flutter-delivery-efa31.appspot.com"
  },
  "client": [
    {
      "client_info": {
        "mobilesdk_app_id": "1:248452815694:android:188518e5e5a5a79e691c1f",
        "android_client_info": {
          "package_name": "com.example.delivery"
        }
      },
      "oauth_client": [],
      "api_key": [
        {
          "current_key": "AIzaSyBK33vED3MDQ0nCUyVl1whAC-nZ-q7tB_A"
        }
      ],
      "services": {
        "appinvite_service": {
          "other_platform_oauth_client": []
        }
      }
    }
  ],
  "configuration_version": "1"
}